nntm/__init__.py
nntm/base.py
nntm/datasets/__init__.py
nntm/datasets/_numerai_main.py
nntm/datasets/_numerai_main_meta.py
nntm/metrics/__init__.py
nntm/metrics/_numerai.py
nntm/metrics/_scorer.py
nntm/model_selection/__init__.py
nntm/model_selection/_split.py
nntm/model_selection/_validation.py
nntm/model_selection/tests/__init__.py
nntm/model_selection/tests/test_split.py
nntm/utils/__init__.py
nntm/utils/_tags.py
nntm/utils/metaestimators.py
nntm/utils/validation.py
nntm-1.6.2.dist-info/LICENSE
nntm-1.6.2.dist-info/METADATA
nntm-1.6.2.dist-info/WHEEL
nntm-1.6.2.dist-info/top_level.txt
nntm-1.6.2.dist-info/RECORD
