Metadata-Version: 2.1
Name: nntm
Version: 1.6.2
Summary: A set of modules for the Numerai tournament.
Home-page: https://github.com/suud/nntm
Author: Timo Sutterer
Author-email: hi@timo-sutterer.de
License: MIT
Project-URL: Bug Tracker, https://github.com/suud/nntm/issues
Keywords: numerai
Classifier: Development Status :: 3 - Alpha
Classifier: Intended Audience :: Science/Research
Classifier: License :: OSI Approved :: MIT License
Classifier: Operating System :: OS Independent
Classifier: Programming Language :: Python :: 3
Classifier: Programming Language :: Python :: 3 :: Only
Classifier: Programming Language :: Python :: 3.6
Classifier: Programming Language :: Python :: 3.7
Classifier: Programming Language :: Python :: 3.8
Classifier: Programming Language :: Python :: 3.9
Classifier: Topic :: Office/Business :: Financial :: Investment
Classifier: Topic :: Software Development
Classifier: Topic :: Scientific/Engineering
Requires-Python: >=3.6
License-File: LICENSE
Requires-Dist: numerapi (>=2.9.0)
Requires-Dist: pandas (>=1.1.0)
Requires-Dist: pyarrow (>=3.0.0)
Requires-Dist: scikit-learn (>=1.0.0)
